voyager_dev/__init__.py
voyager_dev/create_directory_diagram.py
voyager_dev/voyager_dev.py
voyager_dev-0.0.2.dist-info/METADATA
voyager_dev-0.0.2.dist-info/WHEEL
voyager_dev-0.0.2.dist-info/entry_points.txt
voyager_dev-0.0.2.dist-info/top_level.txt
voyager_dev-0.0.2.dist-info/RECORD
