Metadata-Version: 2.1
Name: voyager-dev
Version: 0.0.2
Summary: A package for coding assistance
Home-page: https://github.com/coyotespike/voyager-dev
Author: Timothy Roy
Author-email: tim@gradientflow.ai
License: UNKNOWN
Platform: UNKNOWN
Classifier: Programming Language :: Python :: 3
Classifier: License :: OSI Approved :: MIT License
Classifier: Operating System :: OS Independent
Requires-Python: >=3.6
